Metadata-Version: 1.0
Name: pman
Version: 2.2.0.4
Summary: (Python) Process Manager
Home-page: https://github.com/FNNDSC/pman
Author: Rudolph Pienaar
Author-email: rudolph.pienaar@gmail.com
License: MIT
Platform: UNKNOWN
